dynamic_characterization/__init__.py
dynamic_characterization/classes.py
dynamic_characterization/dynamic_characterization.py
dynamic_characterization/ipcc_ar6/__init__.py
dynamic_characterization/ipcc_ar6/radiative_forcing.py
dynamic_characterization/ipcc_ar6/data/decay_multipliers.json
dynamic_characterization/ipcc_ar6/data/hodnebrog20.csv
dynamic_characterization/original_temporalis_functions/__init__.py
dynamic_characterization/original_temporalis_functions/radiative_forcing.py
dynamic_characterization-1.2.0.dist-info/licenses/LICENSE
dynamic_characterization-1.2.0.dist-info/METADATA
dynamic_characterization-1.2.0.dist-info/WHEEL
dynamic_characterization-1.2.0.dist-info/top_level.txt
dynamic_characterization-1.2.0.dist-info/RECORD
