Metadata-Version: 2.4
Name: dynamic_characterization
Version: 1.2.0
Summary: Collection of functions for characterizing life cycle inventories with temporal information
Author-email: Timo Diepers <timo.diepers@ltt.rwth-aachen.de>
Maintainer-email: Timo Diepers <timo.diepers@ltt.rwth-aachen.de>
Project-URL: source, https://github.com/brightway-lca/dynamic_characterization
Project-URL: homepage, https://github.com/brightway-lca/dynamic_characterization
Project-URL: tracker, https://github.com/brightway-lca/dynamic_characterization/issues
Classifier: Development Status :: 4 - Beta
Classifier: Programming Language :: Python
Classifier: Programming Language :: Python :: 3
Classifier: Programming Language :: Python :: 3.10
Classifier: Programming Language :: Python :: 3.11
Classifier: Programming Language :: Python :: 3.12
Classifier: Natural Language :: English
Classifier: Operating System :: OS Independent
Classifier: Topic :: Scientific/Engineering
Requires-Python: >=3.9
License-File: LICENSE
Requires-Dist: pandas
Requires-Dist: numpy
Requires-Dist: bw2data
Requires-Dist: loguru
Provides-Extra: testing
Requires-Dist: pytest; extra == "testing"
Requires-Dist: pytest-cov; extra == "testing"
Requires-Dist: python-coveralls; extra == "testing"
Provides-Extra: dev
Requires-Dist: build; extra == "dev"
Requires-Dist: pre-commit; extra == "dev"
Requires-Dist: pylint; extra == "dev"
Requires-Dist: pytest; extra == "dev"
Requires-Dist: pytest-cov; extra == "dev"
Requires-Dist: pytest-randomly; extra == "dev"
Requires-Dist: setuptools; extra == "dev"
Dynamic: license-file
